cidwrap/__init__.py
cidwrap/wrap.py
cidwrap-0.1.0.dist-info/METADATA
cidwrap-0.1.0.dist-info/WHEEL
cidwrap-0.1.0.dist-info/top_level.txt
cidwrap-0.1.0.dist-info/RECORD
